factory_boy_peewee-0.0.4.dist-info/DESCRIPTION.rst
factory_boy_peewee-0.0.4.dist-info/METADATA
factory_boy_peewee-0.0.4.dist-info/RECORD
factory_boy_peewee-0.0.4.dist-info/WHEEL
factory_boy_peewee-0.0.4.dist-info/metadata.json
factory_boy_peewee-0.0.4.dist-info/top_level.txt
factory_peewee/__init__.py
