Metadata-Version: 2.0
Name: factory-boy-peewee
Version: 0.0.4
Summary: peewee support for factory_boy
Home-page: https://github.com/cam-stitt/factory_boy-peewee
Author: Cameron Stitt
Author-email: cameron@cam.st
License: UNKNOWN
Platform: UNKNOWN
Requires-Dist: factory-boy
Requires-Dist: peewee
